easyVisualize
